{
  "permalink": "/blog/2021/05/25/Apache APISIX 2.6.0-Release 正式发布",
  "source": "@site/blog\\2021-05-25-Apache APISIX 2.6.0-Release 正式发布.md",
  "title": "Apache APISIX 2.6.0-Release 正式发布",
  "description": "@spacewander, Core developer of Apache APISIX from Shenzhen Zhiliu Technology Co.",
  "date": "2021-05-25T00:00:00.000Z",
  "formattedDate": "May 25, 2021",
  "tags": [],
  "readingTime": 1.12,
  "truncated": true,
  "prevItem": {
    "title": "基于 Apache APISIX 实现的服务网格项目正式开源",
    "permalink": "/blog/2021/05/31/基于 Apache APISIX 实现的服务网格项目正式开源"
  },
  "nextItem": {
    "title": "Traffic Split in Apache APISIX Ingress Controller",
    "permalink": "/blog/2021/03/27/traffic-split-in-apache-apisix-ingress-controller"
  }
}